pyhermes/__init__.py
pyhermes/decorators.py
pyhermes/exceptions.py
pyhermes/management.py
pyhermes/publishing.py
pyhermes/registry.py
pyhermes/settings.py
pyhermes/subscription.py
pyhermes/utils.py
pyhermes/apps/__init__.py
pyhermes/apps/django/__init__.py
pyhermes/apps/django/config.py
pyhermes/apps/django/models.py
pyhermes/apps/django/urls.py
pyhermes/apps/django/views.py
pyhermes/apps/django/management/__init__.py
pyhermes/apps/django/management/commands/__init__.py
pyhermes/apps/django/management/commands/hermes_test.py
pyhermes/apps/flask/__init__.py
pyhermes/apps/flask/blueprints.py
pyhermes/apps/flask/command.py
pyhermes/apps/flask/config.py
pyhermes-0.7.1.dist-info/licenses/AUTHORS.md
pyhermes-0.7.1.dist-info/licenses/LICENSE
pyhermes-0.7.1.dist-info/METADATA
pyhermes-0.7.1.dist-info/WHEEL
pyhermes-0.7.1.dist-info/top_level.txt
pyhermes-0.7.1.dist-info/RECORD
