Metadata-Version: 2.4
Name: pyhermes
Version: 0.7.1
Summary: The Python interface to the Hermes message broker.
Author-email: Allegrogroup <pylabs@allegro.pl>
License-Expression: Apache-2.0
Project-URL: Homepage, https://github.com/allegro/pyhermes
Keywords: pyhermes
Classifier: Development Status :: 4 - Beta
Classifier: Framework :: Django
Classifier: Framework :: Django :: 1.7
Classifier: Framework :: Django :: 1.8
Classifier: Framework :: Django :: 1.9
Classifier: Framework :: Django :: 3.1
Classifier: Intended Audience :: Developers
Classifier: Natural Language :: English
Classifier: Programming Language :: Python :: 2
Classifier: Programming Language :: Python :: 2.7
Classifier: Programming Language :: Python :: 3
Classifier: Programming Language :: Python :: 3.9
Requires-Python: >=3.9
License-File: LICENSE
License-File: AUTHORS.md
Requires-Dist: six
Requires-Dist: requests
Dynamic: license-file
